{"type":"PR","pr":{"number":2,"head":"c517e9351ca494bf1c5115d6a3f217d17701e198"},"user":"chris","status":"draft","branch":"cms/indexiq-etfs-microsite","collection":"portfolio","title":"IndexIQ ETFs Microsite","description":"Essential resource for a large marketing campaign","objects":{"entry":{"path":"src/pages/portfolio/indexiq-etfs-microsite.md","sha":"40ae9f3676419b032345eb53fdef426e029e5274"},"files":[{"path":"/static/img/indexiq-microsite.jpg","sha":"211159c6b602f58da24623a10a00745f83b6c9aa"}]},"timeStamp":"2018-11-21T21:29:35.203Z"}